README.md
setup.py
azdvop/AzDevOps.py
azdvop/__init__.py
azdvop/httpclient.py
azdvop/organization.py
azdvop/project.py
azdvop/redishttp.py
azdvop/subscription.py
pyazdvops.egg-info/PKG-INFO
pyazdvops.egg-info/SOURCES.txt
pyazdvops.egg-info/dependency_links.txt
pyazdvops.egg-info/not-zip-safe
pyazdvops.egg-info/requires.txt
pyazdvops.egg-info/top_level.txt