Metadata-Version: 1.1
Name: pyazdvops
Version: 1.0.4
Summary: Library for Azure DevOps API for Python
Home-page: https://github.com/rockraft7/pyazdevops
Author: Faizal Sidek
Author-email: faizal.sidek@gmail.com
License: Free for non-commercial use
Keywords: Azure,DevOps,Python,API
Platform: UNKNOWN
Classifier: Development Status :: 3 - Alpha
Classifier: Intended Audience :: Developers
Classifier: Topic :: Software Development :: Libraries
Classifier: License :: Free for non-commercial use
Classifier: Natural Language :: English
Classifier: Programming Language :: Python :: 2.7
